
[{"content":" ","date":"23 April 2025","externalUrl":null,"permalink":"/games/3pointcontest/","section":"Games","summary":"See how many three pointers you can make.","title":"3 Point Contest","type":"games"},{"content":"","date":"23 April 2025","externalUrl":null,"permalink":"/article/ar-demos/","section":"Articles","summary":"","title":"AR Demos","type":"article"},{"content":" ","date":"23 April 2025","externalUrl":null,"permalink":"/article/ar-info/","section":"Articles","summary":"","title":"AR Info!","type":"article"},{"content":"","date":"23 April 2025","externalUrl":null,"permalink":"/article/","section":"Articles","summary":"","title":"Articles","type":"article"},{"content":"","date":"23 April 2025","externalUrl":null,"permalink":"/article/contact/","section":"Articles","summary":"","title":"Contact","type":"article"},{"content":" ","date":"23 April 2025","externalUrl":null,"permalink":"/games/fieldgoal/","section":"Games","summary":"Whack as many moles as you can within the time limit.","title":"Field Goal Kick","type":"games"},{"content":"","date":"23 April 2025","externalUrl":null,"permalink":"/games/","section":"Games","summary":"","title":"Games","type":"games"},{"content":"","date":"23 April 2025","externalUrl":null,"permalink":"/article/games-info/","section":"Articles","summary":"","title":"Games Info","type":"article"},{"content":" ","date":"23 April 2025","externalUrl":null,"permalink":"/games/jumpup/","section":"Games","summary":"Whack as many moles as you can within the time limit.","title":"Jump Up","type":"games"},{"content":"","date":"23 April 2025","externalUrl":null,"permalink":"/article/pricing/","section":"Articles","summary":"","title":"Pricing","type":"article"},{"content":" ","date":"23 April 2025","externalUrl":null,"permalink":"/games/stack/","section":"Games","summary":"Stack blocks, but don\u0026rsquo;t let them topple.","title":"Stack","type":"games"},{"content":"A 3D team for marketing teams.\n","date":"23 April 2025","externalUrl":null,"permalink":"/","section":"Welcome","summary":"","title":"Welcome","type":"page"},{"content":" ","date":"23 April 2025","externalUrl":null,"permalink":"/games/whackamole/","section":"Games","summary":"Whack as many moles as you can within the time limit.","title":"Whack-a-mole","type":"games"},{"content":"","externalUrl":null,"permalink":"/authors/","section":"Authors","summary":"","title":"Authors","type":"authors"},{"content":"","externalUrl":null,"permalink":"/categories/","section":"Categories","summary":"","title":"Categories","type":"categories"},{"content":"","externalUrl":null,"permalink":"/series/","section":"Series","summary":"","title":"Series","type":"series"},{"content":"","externalUrl":null,"permalink":"/tags/","section":"Tags","summary":"","title":"Tags","type":"tags"}]